klarg.py
klarg-1.1.0.dist-info/LICENSE
klarg-1.1.0.dist-info/METADATA
klarg-1.1.0.dist-info/WHEEL
klarg-1.1.0.dist-info/top_level.txt
klarg-1.1.0.dist-info/RECORD
