Metadata-Version: 2.1
Name: klarg
Version: 1.1.0
Summary: A simple command line argument parsing library
Home-page: https://github.com/tominekan/klarg
Author: Tomi Adenekan
Author-email: tominekan@outlook.com
License: UNKNOWN
Project-URL: Bug Tracker, https://github.com/tominekan/klarg/issues
Project-URL: Documentation, https://github.com/tominekan/klarg/blob/main/DOCS.md
Platform: UNKNOWN
Classifier: Programming Language :: Python :: 3.7
Classifier: Programming Language :: Python :: 3.8
Classifier: Programming Language :: Python :: 3.9
Classifier: License :: OSI Approved :: MIT License
Classifier: Operating System :: OS Independent
Classifier: Development Status :: 5 - Production/Stable
Requires-Python: >=3.7
